google_cloud_happybase-0.32.1-py3.7-nspkg.pth
google/cloud/happybase/__init__.py
google/cloud/happybase/batch.py
google/cloud/happybase/connection.py
google/cloud/happybase/pool.py
google/cloud/happybase/table.py
google_cloud_happybase-0.32.1.dist-info/LICENSE
google_cloud_happybase-0.32.1.dist-info/METADATA
google_cloud_happybase-0.32.1.dist-info/WHEEL
google_cloud_happybase-0.32.1.dist-info/namespace_packages.txt
google_cloud_happybase-0.32.1.dist-info/top_level.txt
google_cloud_happybase-0.32.1.dist-info/RECORD
