Metadata-Version: 2.1
Name: google-cloud-happybase
Version: 0.32.1
Summary: Client library for Google Cloud Bigtable: HappyBase layer
Home-page: https://github.com/googleapis/google-cloud-python-happybase
Author: Google Cloud Platform
Author-email: googleapis-publisher@google.com
License: Apache 2.0
Platform: Posix; MacOS X; Windows
Classifier: Development Status :: 4 - Beta
Classifier: Intended Audience :: Developers
Classifier: License :: OSI Approved :: Apache Software License
Classifier: Operating System :: OS Independent
Classifier: Programming Language :: Python :: 2
Classifier: Programming Language :: Python :: 2.7
Classifier: Programming Language :: Python :: 3
Classifier: Programming Language :: Python :: 3.4
Classifier: Programming Language :: Python :: 3.5
Classifier: Programming Language :: Python :: 3.6
Classifier: Programming Language :: Python :: 3.7
Classifier: Topic :: Internet
Requires-Python: >=2.7,!=3.0.*,!=3.1.*,!=3.2.*,!=3.3.*
Requires-Dist: google-cloud-bigtable (>=0.31.0)
